Dualport_SRAM.v
module Dualport_SRAM(clk, cs, write, read, address, data_in, data_out);
input clk, cs, write, read;
input [3:0]data_in;input [7:0]address;
output reg [3:0]data_out;
reg [3:0]memory[255:0];

always @ (posedge clk)
begin
    if(~cs)
        data_out<= 4'b0000;
    else begin
        if(write)
            memory[address] <= data_in;
        if (read)
            data_out <= memory[address];
    end
end
endmodule

Dualport_SRAM_tb.v
`timescale 1ns/1ps
`include "Dualport_SRAM.v"

module Dualport_SRAM_tb;
reg clk;
reg cs;
reg write;
reg read;
reg [7:0]address;
reg [3:0]data_in;

wire [3:0]data_out;

Dualport_SRAM uut(clk, cs, write, read, address, data_in, data_out);
    
    initial begin
        $dumpfile("Dualport_SRAM_tb.vcd");
        $dumpvars(0,Dualport_SRAM_tb);
        clk = 0;
        cs = 0;
        write = 0;
        read = 0;
        address = 0;
        data_in = 0;
        #100;
        cs =1;
        write = 1;
        read = 0;
        data_in = 4'b0001;
        address = 4'b0001;
        #10;
        data_in = 4'b0010;
        address = 4'b0010;
        #10;
        read =1;
        write = 0;
        address = 4'b0001;
        #10;
        address = 4'b0010;
        #150;
        $finish;

    end
    always #5 clk = ~(clk);
    initial begin
    $display("Simulation starts");
    // $monitor("Time = %4d  In = %b  LR = %b  n = %b  Out = %b",$time,In,LR,n,Out);
    end
endmodule

Dualport_SRAM_tb.vcd
$date
	Wed Feb 05 00:46:20 2025
$end
$version
	Icarus Verilog
$end
$timescale
	1ps
$end
$scope module Dualport_SRAM_tb $end
$var wire 4 ! data_out [3:0] $end
$var reg 8 " address [7:0] $end
$var reg 1 # clk $end
$var reg 1 $ cs $end
$var reg 4 % data_in [3:0] $end
$var reg 1 & read $end
$var reg 1 ' write $end
$scope module uut $end
$var wire 8 ( address [7:0] $end
$var wire 1 # clk $end
$var wire 1 $ cs $end
$var wire 4 ) data_in [3:0] $end
$var wire 1 & read $end
$var wire 1 ' write $end
$var reg 4 * data_out [3:0] $end
$upscope $end
$upscope $end
$enddefinitions $end
$comment Show the parameter values. $end
$dumpall
$end
#0
$dumpvars
bx *
b0 )
b0 (
0'
0&
b0 %
0$
0#
b0 "
bx !
$end
#5000
b0 !
b0 *
1#
#10000
0#
#15000
1#
#20000
0#
#25000
1#
#30000
0#
#35000
1#
#40000
0#
#45000
1#
#50000
0#
#55000
1#
#60000
0#
#65000
1#
#70000
0#
#75000
1#
#80000
0#
#85000
1#
#90000
0#
#95000
1#
#100000
0#
b1 "
b1 (
b1 %
b1 )
1'
1$
#105000
1#
#110000
0#
b10 "
b10 (
b10 %
b10 )
#115000
1#
#120000
0#
b1 "
b1 (
0'
1&
#125000
b1 !
b1 *
1#
#130000
0#
b10 "
b10 (
#135000
b10 !
b10 *
1#
